rrfpost/__init__.py
rrfpost/__main__.py
rrfpost/version.py
rrfpost-0.10.4.dist-info/LICENSE
rrfpost-0.10.4.dist-info/METADATA
rrfpost-0.10.4.dist-info/WHEEL
rrfpost-0.10.4.dist-info/entry_points.txt
rrfpost-0.10.4.dist-info/top_level.txt
rrfpost-0.10.4.dist-info/RECORD
