Metadata-Version: 2.1
Name: rrfpost
Version: 0.10.4
Summary: CLI tool for post-processing RRF/Duet gcode files
Home-page: https://github.com/adammhaile/RRFPost
Author: Adam Haile
Author-email: adammhaile@gmail.com
License: GNU Affero General Public License v3 or later (AGPLv3+)
Classifier: Development Status :: 4 - Beta
Classifier: Programming Language :: Python :: 3.7
Classifier: Programming Language :: Python :: 3.8
Classifier: Programming Language :: Python :: 3.9
Classifier: Programming Language :: Python :: 3.10
Classifier: Environment :: Console
Classifier: License :: OSI Approved :: GNU Affero General Public License v3 or later (AGPLv3+)
Classifier: Natural Language :: English
License-File: LICENSE
